remarkable_highlights/__init__.py
remarkable_highlights/extract.py
remarkable_highlights/parsing.py
remarkable_highlights-0.1.3.dist-info/entry_points.txt
remarkable_highlights-0.1.3.dist-info/WHEEL
remarkable_highlights-0.1.3.dist-info/METADATA
remarkable_highlights-0.1.3.dist-info/RECORD
