Metadata-Version: 2.1
Name: remarkable-highlights
Version: 0.1.3
Summary: Extract highlights from PDFs exported from the reMarkable web interface.
Home-page: https://github.com/benlongo/remarkable-highlights
License: MIT
Keywords: remarkable-tablet,remarkable
Author: Ben Longo
Author-email: benlongo9807@gmail.com
Requires-Python: >=3.8,<4.0
Classifier: Development Status :: 4 - Beta
Classifier: Environment :: Console
Classifier: License :: OSI Approved :: MIT License
Classifier: Programming Language :: Python :: 3
Classifier: Programming Language :: Python :: 3.8
Classifier: Topic :: Multimedia :: Graphics :: Graphics Conversion
Classifier: Topic :: Utilities
Provides-Extra: debug
Requires-Dist: PyMuPDF (>=1.16.17,<2.0.0)
Requires-Dist: click (>=7.1.1,<8.0.0)
Requires-Dist: descartes (>=1.1.0,<2.0.0); extra == "debug"
Requires-Dist: matplotlib (>=3.2.1,<4.0.0); extra == "debug"
Requires-Dist: shapely (>=1.7.0,<2.0.0)
Project-URL: Repository, https://github.com/benlongo/remarkable-highlights
